tgsart/__init__.py
tgsart-0.1.3.dist-info/LICENSE
tgsart-0.1.3.dist-info/METADATA
tgsart-0.1.3.dist-info/WHEEL
tgsart-0.1.3.dist-info/top_level.txt
tgsart-0.1.3.dist-info/RECORD
