Metadata-Version: 2.1
Name: tgsart
Version: 0.1.3
Summary: Making Telegram Stickers as ASCII Art representation
Home-page: https://github.com/mishimastar/tg-stickers-ascii-art
Author: Sergey Saltykov
Author-email: mishimastar3000@gmail.com
License: MIT
Project-URL: Documentation, https://github.com/mishimastar/tg-stickers-ascii-art
Project-URL: Bug Tracker, https://github.com/mishimastar/tg-stickers-ascii-art/issues
Keywords: telegram,stickers,ascii,art,webp
Classifier: Development Status :: 4 - Beta
Classifier: Intended Audience :: Developers
Classifier: Operating System :: OS Independent
Classifier: Programming Language :: Python :: 3
Classifier: Programming Language :: Python :: 3 :: Only
Classifier: License :: OSI Approved :: MIT License
Requires-Python: ~=3.7
License-File: LICENSE
Requires-Dist: numpy (>=1.22.0)
Requires-Dist: Pillow (>=8.4.0)
Requires-Dist: webp (>=0.1.4)
